.gitignore
.svnignore
CHANGES.rst
CONTRIBUTORS.rst
MANIFEST.in
README.rst
setup.cfg
setup.py
docs/INSTALL.txt
docs/LICENSE.GPL
docs/LICENSE.txt
slc/__init__.py
slc.linkcollection.egg-info/PKG-INFO
slc.linkcollection.egg-info/SOURCES.txt
slc.linkcollection.egg-info/dependency_links.txt
slc.linkcollection.egg-info/entry_points.txt
slc.linkcollection.egg-info/namespace_packages.txt
slc.linkcollection.egg-info/not-zip-safe
slc.linkcollection.egg-info/requires.txt
slc.linkcollection.egg-info/top_level.txt
slc/linkcollection/__init__.py
slc/linkcollection/configure.zcml
slc/linkcollection/interfaces.py
slc/linkcollection/browser/__init__.py
slc/linkcollection/browser/arrow.png
slc/linkcollection/browser/configure.zcml
slc/linkcollection/browser/edit_box.gif
slc/linkcollection/browser/linkbox.pt
slc/linkcollection/browser/linkbox_edit.py
slc/linkcollection/browser/linkcollection.css
slc/linkcollection/browser/linkcollection.js
slc/linkcollection/browser/linkcollection_view.pt
slc/linkcollection/browser/linkcollection_view.py
slc/linkcollection/browser/viewlets.py
slc/linkcollection/profiles/default/browserlayer.xml
slc/linkcollection/profiles/default/cssregistry.xml
slc/linkcollection/profiles/default/jsregistry.xml
slc/linkcollection/profiles/default/viewlets.xml