Metadata-Version: 1.1
Name: slc.linkcollection
Version: 1.4.2
Summary: A viewlet displaying links to subdocuments and quickly loading their content via jquery
Home-page: http://svn.plone.org/svn/plone/plone.example
Author: Syslab.com GmbH
Author-email: info@syslab.com
License: GPL + EUPL
Keywords: viewlet links jquery subnavigation
Platform: UNKNOWN
Classifier: Framework :: Plone
Classifier: Programming Language :: Python
Classifier: Topic :: Software Development :: Libraries :: Python Modules
Classifier: License :: OSI Approved :: GNU General Public License (GPL)
Classifier: License :: OSI Approved :: European Union Public Licence 1.1 (EUPL 1.1)
